sarawater/IHA.py
sarawater/__init__.py
sarawater/habitat.py
sarawater/reach.py
sarawater/scenarios.py
sarawater/sediment_load.py
sarawater/utils.py
sarawater/visualization.py
sarawater-2.1.0.dist-info/licenses/LICENSE
sarawater-2.1.0.dist-info/METADATA
sarawater-2.1.0.dist-info/WHEEL
sarawater-2.1.0.dist-info/top_level.txt
sarawater-2.1.0.dist-info/RECORD
